slothql/__init__.py
slothql/config.py
slothql/conftest.py
slothql/exceptions.py
slothql/query.py
slothql/schema.py
slothql/selections.py
slothql/template.py
slothql/django/__init__.py
slothql/django/queryset.py
slothql/django/views.py
slothql/django/types/__init__.py
slothql/django/types/model.py
slothql/django/types/registry.py
slothql/django/types/scalars.py
slothql/django/utils/__init__.py
slothql/django/utils/model.py
slothql/django/utils/request.py
slothql/fields/__init__.py
slothql/fields/datetime.py
slothql/fields/field.py
slothql/fields/list.py
slothql/fields/resolver.py
slothql/fields/scalars.py
slothql/templates/graphiql.html
slothql/types/__init__.py
slothql/types/object.py
slothql/utils/__init__.py
slothql/utils/attr.py
slothql/utils/laziness.py
slothql/utils/query.py
slothql/utils/singleton.py
slothql-0.1.0a0.dist-info/DESCRIPTION.rst
slothql-0.1.0a0.dist-info/METADATA
slothql-0.1.0a0.dist-info/RECORD
slothql-0.1.0a0.dist-info/WHEEL
slothql-0.1.0a0.dist-info/metadata.json
slothql-0.1.0a0.dist-info/top_level.txt
